{
  "objectInfo" : {
    "id" : "eG9ts9K9Ig6hQPRaQV8Vu4",
    "name" : "apDasTest",
    "type" : "AI_CONNECTION",
    "metadata" : {
      "modelVersion" : {
        "major" : 1,
        "minor" : 0
      },
      "repoInfo" : {
        "repoHandle" : "354STu0kMVX3cjk-gt-51062738-2022-07-28T19:27:09.288Z::conn.xml"
      },
      "contextAttributes" : null,
      "additionalInfo" : {
        "description" : "",
        "contentType" : "application/json; charset=utf-8",
        "documentState" : "VALID"
      }
    }
  },
  "dataFileExtension" : "xml",
  "objectRefs" : [ {
    "id" : "7bYfvAaTAUvgylWWj0o1eu",
    "name" : "dasDb2As400",
    "type" : "AI_SERVICE_CONNECTOR",
    "metadata" : {
      "modelVersion" : {
        "major" : 1,
        "minor" : 0
      },
      "repoInfo" : {
        "repoHandle" : "Q9FkPaaaaaaaaa-gt-26539504-2022-07-27T10:54:08.968Z::svc.xml"
      },
      "contextAttributes" : null,
      "additionalInfo" : {
        "description" : "",
        "contentType" : "application/json; charset=utf-8",
        "documentState" : "VALID"
      }
    },
    "path" : "/Explore/sribatsa/Service Connectors"
  } ]
}