<aetgt:getResponse xmlns:aetgt="http://schemas.active-endpoints.com/appmodules/repository/2010/10/avrepository.xsd"
                   xmlns:types1="http://schemas.active-endpoints.com/appmodules/repository/2010/10/avrepository.xsd">
   <types1:Item>
      <types1:EntryId>SUXL86zqzm5Y6tM-gt-8224082-2023-02-21T07:08:37.194Z::gt.xml</types1:EntryId>
      <types1:Name>GUIDE_NONSAP_ACCOUNT_ATTACHMENT_UPL</types1:Name>
      <types1:MimeType>application/xml+screenflow</types1:MimeType>
      <types1:Description/>
      <types1:AppliesTo>Salesforce:Account</types1:AppliesTo>
      <types1:Tags/>
      <types1:VersionLabel>1.0</types1:VersionLabel>
      <types1:State>CURRENT</types1:State>
      <types1:ProcessGroup/>
      <types1:CreatedBy>GcsCloudAdminSri</types1:CreatedBy>
      <types1:CreationDate>2023-02-21T07:08:37Z</types1:CreationDate>
      <types1:ModifiedBy>GcsCloudAdminSri</types1:ModifiedBy>
      <types1:ModificationDate>2023-02-21T07:20:07Z</types1:ModificationDate>
      <types1:PublicationStatus>out-of-date</types1:PublicationStatus>
      <types1:PublishedBy>GcsCloudAdminSri</types1:PublishedBy>
      <types1:PublicationDate>2023-02-21T07:20:14Z</types1:PublicationDate>
      <types1:PublishedContributionId>project:/sf.GUIDE_NONSAP_ACCOUNT_ATTACHMENT_UPL/GUIDE_NONSAP_ACCOUNT_ATTACHMENT_UPL.xml</types1:PublishedContributionId>
      <types1:AutosaveExists>false</types1:AutosaveExists>
      <types1:Entry>
         <avosScreenflow xmlns="http://schemas.active-endpoints.com/appmodules/screenflow/2010/10/avosScreenflow.xsd"
                         xmlns:list="urn:activevos:spi:list:functions"
                         allowRestart="true"
                         displayName="GUIDE_NONSAP_ACCOUNT_ATTACHMENT_UPL"
                         doneOnEndStep="false"
                         name="GUIDE_NONSAP_ACCOUNT_ATTACHMENT_UPL"
                         runAsUser="$current">
            <description/>
            <appliesTo>Salesforce:Account</appliesTo>
            <tags/>
            <generator>Informatica Process Designer 11</generator>
            <output>
               <field description="" name="output" type="string">
                  <options>
                     <option name="required">false</option>
                  </options>
               </field>
            </output>
            <runOn target="desktop"/>
            <notes/>
            <deployment/>
            <sendFeedback>
               <emailTo/>
            </sendFeedback>
            <flow>
               <startScreen id="jd300kk3">
                  <title>Start</title>
                  <body contentType="text/html"/>
                  <actions>
                     <action alt="" id="jd300kk3_ledwlc4a" targetScreen="ledwlc4a">
                        <text>Continue</text>
                     </action>
                  </actions>
                  <screenData skipIfRequiredFilled="true"/>
               </startScreen>
               <screen id="ledwlc4g">
                  <title>Screen 1</title>
                  <body contentType="text/html">&lt;p&gt;This is a test Screen&lt;/p&gt;</body>
                  <actionPrompt/>
                  <actions>
                     <action alt="" id="ledwlc4g_jd4cwa59" targetScreen="jd4cwa59">
                        <text>Continue</text>
                     </action>
                  </actions>
               </screen>
               <endScreen id="jd4cwa59">
                  <title>End</title>
                  <body contentType="text/html"/>
                  <redirectTo type="current_object"/>
                  <screenActionLabel>
                     <text/>
                  </screenActionLabel>
               </endScreen>
               <assignment id="ledwlc4a">
                  <title>Assignment to output</title>
                  <operation source="constant" to="output.output">OK</operation>
                  <actions>
                     <action alt="" id="ledwlc4a_ledwlc4g" targetScreen="ledwlc4g">
                        <text>Continue</text>
                     </action>
                  </actions>
               </assignment>
            </flow>
         </avosScreenflow>
      </types1:Entry>
      <types1:GUID>1CCE7HXXSZllWDlYfNSjex</types1:GUID>
      <types1:DisplayName>GUIDE_NONSAP_ACCOUNT_ATTACHMENT_UPL</types1:DisplayName>
   </types1:Item>
   <types1:CurrentServerDateTime>2023-07-24T12:27:18.019Z</types1:CurrentServerDateTime>
</aetgt:getResponse>
