{
  "objectInfo" : {
    "id" : "3jOYNX7DKUIlvvwqqCrpW4",
    "name" : "KafkalatestappFieldsappStudentVisaCa",
    "type" : "PROCESS_OBJECT",
    "metadata" : {
      "modelVersion" : {
        "major" : 1,
        "minor" : 0
      },
      "repoInfo" : {
        "repoHandle" : "kPtokMJoGsF4Xkg-gt-39645913-2022-09-20T11:54:10.163Z::po.xml"
      },
      "contextAttributes" : null,
      "additionalInfo" : {
        "description" : "This object was generated from [Kafkalatestapp_fieldsapp_student_visa_ca complex type] located in the [Kafka.json.xsd] source XML schema.",
        "contentType" : "application/json; charset=utf-8",
        "documentState" : "VALID"
      }
    }
  },
  "dataFileExtension" : "xml",
  "objectRefs" : [ ]
}