{
  "objectInfo" : {
    "id" : "95IekkvGqN1bQwt916vUKB",
    "name" : "sp-tf-XQuery",
    "type" : "TASKFLOW",
    "metadata" : {
      "modelVersion" : {
        "major" : 1,
        "minor" : 0
      },
      "repoInfo" : {
        "repoHandle" : "18pNz6HKoJBUhty-gt-29823161-2021-05-18T13:24:49.854Z::tf.xml"
      },
      "contextAttributes" : null,
      "additionalInfo" : {
        "description" : "",
        "contentType" : "application/json; charset=utf-8",
        "documentState" : "VALID"
      }
    }
  },
  "dataFileExtension" : "xml",
  "objectRefs" : [ ]
}