<aetgt:getResponse xmlns:aetgt="http://schemas.active-endpoints.com/appmodules/repository/2010/10/avrepository.xsd"
                   xmlns:types1="http://schemas.active-endpoints.com/appmodules/repository/2010/10/avrepository.xsd">
   <types1:Item>
      <types1:EntryId>Brx8AyNnQMMnGbc-gt-100087999-2021-07-09T07:29:47.439Z::conn.xml</types1:EntryId>
      <types1:Name>repro-conn-tcPcm-case-03125542</types1:Name>
      <types1:ParentFlowIds>eD6HKoJBUhtycot-gt-98584974-2021-07-09T07:25:54.069Z::pd.xml</types1:ParentFlowIds>
      <types1:MimeType>application/xml+connection</types1:MimeType>
      <types1:Description/>
      <types1:AppliesTo/>
      <types1:Tags>.agent:SribatsaAgentGroup</types1:Tags>
      <types1:VersionLabel>1.0</types1:VersionLabel>
      <types1:State>CURRENT</types1:State>
      <types1:ProcessGroup/>
      <types1:CreatedBy>GcsCloudAdminSri</types1:CreatedBy>
      <types1:CreationDate>2021-07-09T07:29:47Z</types1:CreationDate>
      <types1:ModifiedBy/>
      <types1:PublicationStatus>published</types1:PublicationStatus>
      <types1:PublishedBy>GcsCloudAdminSri</types1:PublishedBy>
      <types1:PublicationDate>2021-07-09T08:20:30Z</types1:PublicationDate>
      <types1:PublishedContributionId>project:/rt.connection/repro-conn-tcPcm-case-03125542/repro-conn-tcPcm-case-03125542.conn.xml</types1:PublishedContributionId>
      <types1:AutosaveExists>false</types1:AutosaveExists>
      <types1:Entry>
         <connection xmlns="http://schemas.informatica.com/socrates/data-services/2014/04/avosConnections.xsd"
                     displayName="repro-conn-tcPcm-case-03125542"
                     label="repro-conn-tcPcm-case-03125542"
                     name="repro-conn-tcPcm-case-03125542">
            <description/>
            <tags>.agent:SribatsaAgentGroup</tags>
            <agent>SribatsaAgentGroup</agent>
            <attributes>
               <attribute encrypted="false"
                          name="host"
                          value="https://na1.ai.dm-us.informaticacloud.com/active-bpel/public/rt/4LIW2E9dmSefqixInUK4on/repro-proc-case-03125542"/>
            </attributes>
            <businessConnector xmlns="http://schemas.informatica.com/appmodules/screenflow/2014/04/avosConnectors.xsd"
                               agentOnly="true"
                               connectorPath="project:/rt.connector/repro_serviceConn_TcPCM_case_03125542/repro_serviceConn_TcPCM_case_03125542_svcDef.xml"
                               guid="8xgkAtvKjCPbe6KO5scvYh"
                               name="repro-serviceConn-TcPCM-case-03125542"
                               supportsConnectionTest="false"
                               uuid="b2eed51f-08be-44f5-82fb-4802e4783431">
               <description/>
            </businessConnector>
         </connection>
      </types1:Entry>
      <types1:GUID>95v2nOsd1kIktXsOrEcYal</types1:GUID>
      <types1:DisplayName>repro-conn-tcPcm-case-03125542</types1:DisplayName>
   </types1:Item>
   <types1:CurrentServerDateTime>2023-07-24T12:27:15.592Z</types1:CurrentServerDateTime>
</aetgt:getResponse>
